float_on_py/__init__.py
float_on_py/clients/__init__.py
float_on_py/config/__init__.py
float_on_py/people/__init__.py
float_on_py/projects/__init__.py
float_on_py/tasks/__init__.py
float_on_py-0.0.2.dist-info/LICENSE
float_on_py-0.0.2.dist-info/METADATA
float_on_py-0.0.2.dist-info/WHEEL
float_on_py-0.0.2.dist-info/top_level.txt
float_on_py-0.0.2.dist-info/RECORD
